cartesian_viz/draw_descriptors.py
cartesian_viz/engine.py
cartesian_viz/sample_test.py
cartesian_viz-1.0.1.dist-info/LICENSE
cartesian_viz-1.0.1.dist-info/METADATA
cartesian_viz-1.0.1.dist-info/WHEEL
cartesian_viz-1.0.1.dist-info/top_level.txt
cartesian_viz-1.0.1.dist-info/RECORD
